jirachlog/__init__.py
jirachlog/config.py
jirachlog/git.py
jirachlog/ver.py
jirachlog-1.4.0.data/scripts/jirachlog
jirachlog-1.4.0.dist-info/LICENSE
jirachlog-1.4.0.dist-info/METADATA
jirachlog-1.4.0.dist-info/WHEEL
jirachlog-1.4.0.dist-info/top_level.txt
jirachlog-1.4.0.dist-info/RECORD
