Metadata-Version: 2.1
Name: jirachlog
Version: 1.4.0
Summary: Creates a basic changelog using git and Jira
Home-page: https://github.com/digitalroute/jirachlog
Author: Marcus Johansson
Author-email: polarn@gmail.com
License: APACHE
License-File: LICENSE
Requires-Dist: jira (>=3.0.0)
